paramlogger/__init__.py
paramlogger/constants.py
paramlogger/file_utils.py
paramlogger/utils.py
param_logger-0.0.1.post1.dist-info/LICENSE
param_logger-0.0.1.post1.dist-info/METADATA
param_logger-0.0.1.post1.dist-info/WHEEL
param_logger-0.0.1.post1.dist-info/top_level.txt
param_logger-0.0.1.post1.dist-info/RECORD
