Metadata-Version: 2.1
Name: param-logger
Version: 0.0.1.post1
Summary: This library helps logging the inputs and outputs of a method just by adding a decorator on that method.
Home-page: https://github.com/vivek-dani/param-logger
Author: Vivek Dani
Classifier: Intended Audience :: Developers
Classifier: License :: OSI Approved :: MIT License
Classifier: Programming Language :: Python :: 3
Classifier: Operating System :: OS Independent
Requires-Python: >=3.8
License-File: LICENSE
Provides-Extra: dev
Requires-Dist: twine ; extra == 'dev'
Requires-Dist: wheel ; extra == 'dev'
Provides-Extra: test
Requires-Dist: pytest ; extra == 'test'
